[{"['red_panda', 'stand_left', 'red_panda']": [0, 165], "score": 13.441895771026614}, {"['red_panda', 'ride', 'red_panda']": [0, 165], "score": 12.339395825068156}, {"['red_panda', 'walk_left', 'red_panda']": [0, 165], "score": 11.986531551678976}, {"['red_panda', 'stand_front', 'red_panda']": [0, 165], "score": 11.679156708717347}, {"['red_panda', 'walk_left', 'red_panda']": [0, 165], "score": 11.525819206237793}, {"['red_panda', 'stand_right', 'red_panda']": [0, 165], "score": 13.581086003780365}, {"['red_panda', 'taller', 'red_panda']": [0, 165], "score": 13.123567853655135}, {"['red_panda', 'taller', 'red_panda']": [0, 165], "score": 12.772727520125251}, {"['red_panda', 'ride', 'red_panda']": [0, 165], "score": 12.334213763191586}, {"['red_panda', 'ride', 'red_panda']": [0, 165], "score": 11.84017077287038}, {"['watercraft', 'larger', 'red_panda']": [0, 255], "score": 11.029350936412811}, {"['watercraft', 'taller', 'red_panda']": [0, 255], "score": 10.752803683280945}, {"['watercraft', 'stand_right', 'red_panda']": [0, 240], "score": 10.141075070699056}, {"['watercraft', 'stand_left', 'red_panda']": [0, 240], "score": 8.935805944160178}, {"['watercraft', 'play', 'red_panda']": [0, 240], "score": 8.875165824095408}, {"['watercraft', 'larger', 'red_panda']": [0, 165], "score": 10.567893886566164}, {"['watercraft', 'taller', 'red_panda']": [0, 165], "score": 10.365105247497556}, {"['watercraft', 'stand_left', 'red_panda']": [0, 165], "score": 9.517376263936361}, {"['watercraft', 'stand_right', 'red_panda']": [0, 165], "score": 8.999861611260311}, {"['watercraft', 'ride', 'red_panda']": [0, 165], "score": 8.840989828109743}, {"['red_panda', 'stand_left', 'watercraft']": [0, 105], "score": 9.406347084045409}, {"['red_panda', 'stand_left', 'watercraft']": [0, 105], "score": 8.880241738425362}, {"['red_panda', 'walk_behind', 'watercraft']": [0, 105], "score": 8.692400958802963}, {"['red_panda', 'ride', 'watercraft']": [0, 105], "score": 8.591826995213827}, {"['red_panda', 'stand_right', 'watercraft']": [0, 105], "score": 8.3169766664505}, {"['bicycle', 'stand_left', 'red_panda']": [0, 30], "score": 9.406401634216309}, {"['bicycle', 'taller', 'red_panda']": [0, 30], "score": 8.832382202148438}, {"['bicycle', 'larger', 'red_panda']": [0, 30], "score": 8.59744644165039}, {"['bicycle', 'ride', 'red_panda']": [0, 30], "score": 8.519354820251465}, {"['bicycle', 'sit_above', 'red_panda']": [0, 30], "score": 8.41468620300293}, {"['bicycle', 'taller', 'red_panda']": [0, 30], "score": 9.228170394897461}, {"['bicycle', 'ride', 'red_panda']": [0, 30], "score": 9.104745864868164}, {"['bicycle', 'larger', 'red_panda']": [0, 30], "score": 9.08083724975586}, {"['bicycle', 'stand_left', 'red_panda']": [0, 30], "score": 8.9324951171875}, {"['bicycle', 'stand_right', 'red_panda']": [0, 30], "score": 8.460856437683105}, {"['red_panda', 'stand_left', 'watercraft']": [0, 105], "score": 9.27629005908966}, {"['red_panda', 'stand_right', 'watercraft']": [0, 105], "score": 8.800623257954916}, {"['red_panda', 'ride', 'watercraft']": [0, 105], "score": 8.697434306144713}, {"['red_panda', 'stop_behind', 'watercraft']": [0, 105], "score": 8.391280968983969}, {"['red_panda', 'walk_behind', 'watercraft']": [0, 105], "score": 8.320969486236573}, {"['red_panda', 'ride', 'bicycle']": [0, 30], "score": 8.753589630126953}, {"['red_panda', 'stand_right', 'bicycle']": [0, 30], "score": 8.403634071350098}, {"['red_panda', 'move_beneath', 'bicycle']": [0, 30], "score": 8.143392562866211}, {"['red_panda', 'stand_behind', 'bicycle']": [0, 30], "score": 7.968075275421143}, {"['red_panda', 'sit_right', 'bicycle']": [0, 30], "score": 7.84096097946167}, {"['red_panda', 'move_beneath', 'bicycle']": [0, 30], "score": 8.631758689880371}, {"['red_panda', 'ride', 'bicycle']": [0, 30], "score": 8.493974685668945}, {"['red_panda', 'stand_right', 'bicycle']": [0, 30], "score": 8.451714515686035}, {"['red_panda', 'stand_behind', 'bicycle']": [0, 30], "score": 7.900557994842529}, {"['red_panda', 'stand_left', 'bicycle']": [0, 30], "score": 7.892430782318115}, {"['person', 'ride', 'red_panda']": [30, 90], "score": 9.07006867726644}, {"['person', 'ride', 'red_panda']": [30, 75], "score": 9.376514911651611}, {"['red_panda', 'stand_right', 'person']": [30, 75], "score": 8.913671970367432}, {"['red_panda', 'move_beneath', 'person']": [30, 75], "score": 8.257265090942383}, {"['car', 'stand_left', 'red_panda']": [60, 90], "score": 9.494991302490234}, {"['red_panda', 'stand_right', 'car']": [60, 90], "score": 9.008079528808594}, {"['car', 'ride', 'red_panda']": [60, 105], "score": 8.541302680969238}, {"['car', 'ride', 'red_panda']": [60, 90], "score": 8.470521926879883}, {"['red_panda', 'taller', 'car']": [60, 90], "score": 8.253104209899902}, {"['red_panda', 'ride', 'car']": [60, 105], "score": 8.24552869796753}, {"['car', 'walk_behind', 'red_panda']": [60, 105], "score": 8.202881813049316}, {"['person', 'ride', 'red_panda']": [75, 105], "score": 9.363837242126465}, {"['person', 'ride', 'red_panda']": [75, 105], "score": 9.056489944458008}, {"['red_panda', 'stand_left', 'person']": [75, 105], "score": 8.734075546264648}, {"['red_panda', 'stand_right', 'person']": [75, 105], "score": 8.614477157592773}, {"['person', 'ride', 'red_panda']": [90, 150], "score": 15.272613843282064}, {"['person', 'ride', 'red_panda']": [90, 150], "score": 14.74118709564209}, {"['red_panda', 'move_beneath', 'person']": [90, 150], "score": 13.565644900004068}, {"['red_panda', 'move_beneath', 'person']": [90, 150], "score": 13.54231341679891}, {"['watercraft', 'larger', 'person']": [90, 150], "score": 10.622624397277832}, {"['person', 'ride', 'person']": [90, 120], "score": 10.517291069030762}, {"['person', 'ride', 'person']": [120, 150], "score": 10.473488807678223}, {"['person', 'ride', 'red_panda']": [135, 165], "score": 9.509885787963867}, {"['car', 'ride', 'red_panda']": [135, 165], "score": 9.482954025268555}, {"['person', 'ride', 'red_panda']": [135, 165], "score": 9.319750785827637}, {"['car', 'stand_left', 'red_panda']": [135, 165], "score": 9.26009750366211}, {"['red_panda', 'stand_right', 'car']": [135, 165], "score": 9.146526336669922}, {"['red_panda', 'larger', 'car']": [135, 165], "score": 8.972932815551758}, {"['red_panda', 'ride', 'person']": [135, 165], "score": 8.922046661376953}, {"['red_panda', 'ride', 'person']": [135, 165], "score": 8.551774978637695}, {"['person', 'ride', 'red_panda']": [150, 255], "score": 14.255937894185386}, {"['person', 'ride', 'red_panda']": [150, 210], "score": 13.771262804667154}, {"['red_panda', 'ride', 'red_panda']": [150, 210], "score": 12.886846860249838}, {"['red_panda', 'stand_left', 'red_panda']": [150, 210], "score": 12.760670979817709}, {"['red_panda', 'ride', 'person']": [150, 210], "score": 12.993135452270508}, {"['red_panda', 'ride', 'person']": [150, 255], "score": 12.743960825602214}, {"['watercraft', 'larger', 'red_panda']": [150, 210], "score": 10.329529444376627}, {"['watercraft', 'larger', 'person']": [180, 285], "score": 11.274627208709717}, {"['person', 'ride', 'watercraft']": [180, 240], "score": 11.13500690460205}, {"['person', 'ride', 'person']": [180, 225], "score": 10.59451675415039}, {"['car', 'stand_right', 'red_panda']": [195, 240], "score": 11.177877426147461}, {"['person', 'ride', 'car']": [195, 240], "score": 10.57163953781128}, {"['person', 'ride', 'car']": [195, 240], "score": 10.723396301269531}, {"['car', 'stand_right', 'person']": [195, 240], "score": 10.353215217590332}, {"['car', 'stand_left', 'person']": [195, 240], "score": 10.709659099578857}, {"['red_panda', 'stand_left', 'car']": [195, 225], "score": 10.140486717224121}, {"['car', 'stand_left', 'red_panda']": [195, 255], "score": 10.609569191932678}, {"['red_panda', 'stand_left', 'car']": [195, 240], "score": 10.325811386108398}, {"['watercraft', 'larger', 'car']": [195, 225], "score": 9.318326950073242}, {"['person', 'ride', 'red_panda']": [210, 345], "score": 12.835416078567505}, {"['red_panda', 'stand_left', 'red_panda']": [210, 255], "score": 12.966334342956543}, {"['red_panda', 'taller', 'red_panda']": [210, 255], "score": 12.708425521850586}, {"['car', 'stand_left', 'red_panda']": [210, 255], "score": 11.97720193862915}, {"['red_panda', 'ride', 'person']": [210, 345], "score": 11.846880833307901}, {"['watercraft', 'larger', 'red_panda']": [210, 300], "score": 10.349298095703125}, {"['red_panda', 'stand_right', 'car']": [210, 240], "score": 10.809473037719727}, {"['car', 'stand_right', 'red_panda']": [210, 240], "score": 10.331135749816895}, {"['car', 'stand_left', 'watercraft']": [210, 240], "score": 10.056142807006836}, {"['person', 'ride', 'red_panda']": [225, 270], "score": 13.140015602111816}, {"['red_panda', 'ride', 'person']": [225, 270], "score": 12.464217185974121}, {"['red_panda', 'ride', 'red_panda']": [225, 255], "score": 12.719452857971191}, {"['red_panda', 'stand_right', 'red_panda']": [225, 270], "score": 12.36989450454712}, {"['red_panda', 'taller', 'red_panda']": [225, 255], "score": 11.90951156616211}, {"['red_panda', 'stand_left', 'red_panda']": [225, 270], "score": 12.132558345794678}, {"['watercraft', 'larger', 'red_panda']": [225, 270], "score": 11.099049091339111}, {"['car', 'stand_left', 'red_panda']": [225, 255], "score": 11.07966136932373}, {"['red_panda', 'stand_right', 'red_panda']": [255, 300], "score": 13.057929515838623}, {"['red_panda', 'stand_left', 'red_panda']": [255, 300], "score": 12.824996948242188}, {"['person', 'ride', 'red_panda']": [255, 300], "score": 11.36931848526001}, {"['red_panda', 'ride', 'person']": [255, 300], "score": 10.545729160308838}, {"['car', 'stand_left', 'red_panda']": [255, 300], "score": 11.219303607940674}, {"['red_panda', 'taller', 'car']": [255, 300], "score": 10.748412609100342}, {"['watercraft', 'larger', 'red_panda']": [255, 300], "score": 9.758172988891602}, {"['person', 'ride', 'car']": [255, 285], "score": 10.06367301940918}, {"['car', 'stand_left', 'red_panda']": [255, 300], "score": 9.648797512054443}, {"['red_panda', 'taller', 'car']": [255, 300], "score": 9.566220760345459}, {"['red_panda', 'stand_left', 'watercraft']": [270, 300], "score": 8.744197845458984}, {"['red_panda', 'stand_left', 'watercraft']": [270, 300], "score": 8.347250938415527}, {"['person', 'ride', 'red_panda']": [285, 345], "score": 13.124737421671549}, {"['red_panda', 'stand_left', 'red_panda']": [285, 345], "score": 13.053730010986328}, {"['red_panda', 'stand_right', 'red_panda']": [285, 345], "score": 12.95823891957601}, {"['red_panda', 'move_beneath', 'person']": [285, 345], "score": 11.73176352183024}, {"['person', 'ride', 'person']": [285, 345], "score": 11.549246788024902}, {"['person', 'ride', 'red_panda']": [285, 345], "score": 12.069558103879293}, {"['person', 'ride', 'person']": [285, 345], "score": 11.400293032328287}, {"['red_panda', 'stand_right', 'person']": [285, 345], "score": 11.585570653279623}, {"['person', 'ride', 'red_panda']": [285, 345], "score": 11.596336682637533}, {"['red_panda', 'ride', 'person']": [285, 345], "score": 11.293572743733725}, {"['watercraft', 'larger', 'red_panda']": [315, 345], "score": 10.835092544555664}, {"['watercraft', 'larger', 'red_panda']": [315, 345], "score": 10.650161743164062}]